<?xml version="1.0" encoding="UTF-8"?><extensionAttribute>	<displayName>OS - Spotlight Disabled</displayName>	<displayInCategory>Security Reporting</displayInCategory>	<dataType>string</dataType>	<description>This extension attribute template will verify that spotlight indexing is disabled.</description>	<scriptContentsMac>#!/bin/shlaunchAgent=""menuBar=""indexingStatus=`/usr/bin/mdutil -s / | grep "Indexing"`if [ -f "/System/Library/LaunchAgents/com.apple.Spotlight.plist" ]; thenlaunchAgent="true"elselaunchAgent="false"fiif [ -d "/System/Library/CoreServices/Spotlight.app" ]; thenmenuBar="true"elif [ -d "/System/Library/CoreServices/Search.bundle" ]; thenmenuBar="true"elsemenuBar="false"fiif [ "$launchAgent" == "true" ] || [ "$menubar" == "true" ] || [ "indexingStatus" == "Indexing enabled." ]; thenecho "&lt;result&gt;menuBar: $menuBar LaunchAgent: $launchAgent indexing status: $indexingStatus  -  Fail (Spotlight Enabled)&lt;/result&gt;"elseecho "&lt;result&gt;Pass (Spotlight Disabled)&lt;/result&gt;"fi	</scriptContentsMac></extensionAttribute>